HanLabTools/__init__.py
HanLabTools/io.py
HanLabTools/processing.py
HanLabTools/reporting.py
HanLabTools/version.py
HanLabTools/config/HanLab.cfg
HanLabTools/config/__init__.py
HanLabTools/config/config.py
HanLabTools-0.2.3.dist-info/LICENSE
HanLabTools-0.2.3.dist-info/METADATA
HanLabTools-0.2.3.dist-info/WHEEL
HanLabTools-0.2.3.dist-info/top_level.txt
HanLabTools-0.2.3.dist-info/RECORD
