Metadata-Version: 2.1
Name: HanLabTools
Version: 0.2.3
Summary: Import tools for DNPLab specific to the Han Lab
Home-page: https://github.com/Bridge12Technologies/HanLabTools
Author: Thorsten Maly
Author-email: tmaly@bridge12.com
Project-URL: Tracker, https://github.com/Bridge12Technologies/HanLabTools/issues
Requires-Python: >=3.8
License-File: LICENSE
Requires-Dist: numpy (>=1.24)
